{
    "boxShadow": "{{appsmith.theme.boxShadow.appBoxShadow}}",
    "widgetName": "con_customers",
    "borderColor": "#fff",
    "dynamicPropertyPathList": [
        {"key": "borderRadius"},
        {"key": "boxShadow"}
    ],
    "topRow": 35,
    "bottomRow": 121,
    "parentRowSpace": 10,
    "type": "CONTAINER_WIDGET",
    "shouldScrollContents": false,
    "parentColumnSpace": 19.75,
    "dynamicTriggerPathList": [],
    "leftColumn": 1,
    "dynamicBindingPathList": [
        {"key": "borderRadius"},
        {"key": "boxShadow"}
    ],
    "children": [{
        "labelTextSize": "0.875rem",
        "boxShadow": "none",
        "widgetName": "Canvas114",
        "rightColumn": 632,
        "detachFromLayout": true,
        "widgetId": "3f9j16chhb",
        "containerStyle": "none",
        "topRow": 0,
        "bottomRow": 860,
        "parentRowSpace": 1,
        "isVisible": "true",
        "canExtend": false,
        "type": "CANVAS_WIDGET",
        "version": 1,
        "parentId": "xob2hpn350",
        "minHeight": 870,
        "isLoading": false,
        "parentColumnSpace": 1,
        "dynamicTriggerPathList": [],
        "leftColumn": 0,
        "dynamicBindingPathList": [],
        "borderRadius": "0px"
    }],
    "borderWidth": "0",
    "labelTextSize": "0.875rem",
    "backgroundColor": "#ffffff",
    "rightColumn": 31,
    "dynamicHeight": "FIXED",
    "widgetId": "xob2hpn350",
    "containerStyle": "card",
    "isVisible": "true",
    "version": 1,
    "parentId": "0",
    "isLoading": false,
    "borderRadius": "{{appsmith.theme.borderRadius.appBorderRadius}}",
    "maxDynamicHeight": 9000,
    "minDynamicHeight": 4
}